sruthi/__init__.py
sruthi/client.py
sruthi/errors.py
sruthi/response.py
sruthi/xmlparse.py
sruthi-2.0.0.dist-info/LICENSE.md
sruthi-2.0.0.dist-info/METADATA
sruthi-2.0.0.dist-info/WHEEL
sruthi-2.0.0.dist-info/top_level.txt
sruthi-2.0.0.dist-info/RECORD
